[{"id":"joke-YcvNGmJS","date":"2018-02-02T14:17:04.080Z","caption":"Knock knock!\n    Who's there?\nConfounders\n    Confounders who?\nConfounders epidemiology!","postedToGit":true,"htmlFragment":"<li class=\"pane\">\n  <div class=\"time-stamp entry-meta\">\n    <a href=\"joke-YcvNGmJS.html\">\n      <time datetime=\"2018-02-02T14:17:04.080Z\">2018-2-2 09:17:04</time>\n    </a>\n  </div><div class=\"text-caption\">Knock knock!\n    Who's there?\nConfounders\n    Confounders who?\nConfounders epidemiology!</div>\n</li>","postedSingleVideoPage":true},{"id":"joke-IteMXqNJ","date":"2018-02-02T17:17:02.934Z","caption":"Knock knock!\n    Who's there?\nYale University\n    Yale University who?\nYale university art gallery!","postedToGit":true,"htmlFragment":"<li class=\"pane\">\n  <div class=\"time-stamp entry-meta\">\n    <a href=\"joke-IteMXqNJ.html\">\n      <time datetime=\"2018-02-02T17:17:02.934Z\">2018-2-2 12:17:02</time>\n    </a>\n  </div><div class=\"text-caption\">Knock knock!\n    Who's there?\nYale University\n    Yale University who?\nYale university art gallery!</div>\n</li>","postedSingleVideoPage":true}]