[{"id":"joke-GFQkUcDb","date":"2018-03-06T02:17:03.075Z","caption":"Knock knock!\n    Who's there?\nAvifauna\n    Avifauna who?\nAvifaunal!","postedToGit":true,"htmlFragment":"<li class=\"pane\">\n  <div class=\"time-stamp entry-meta\">\n    <a href=\"joke-GFQkUcDb.html\">\n      <time datetime=\"2018-03-06T02:17:03.075Z\">2018-3-5 21:17:03</time>\n    </a>\n  </div><div class=\"text-caption\">Knock knock!\n    Who's there?\nAvifauna\n    Avifauna who?\nAvifaunal!</div>\n</li>","postedSingleVideoPage":true},{"id":"joke-StlguCwk","date":"2018-03-06T05:17:03.766Z","caption":"Knock knock!\n    Who's there?\nHarvard University\n    Harvard University who?\nHarvard university majors!","postedToGit":true,"htmlFragment":"<li class=\"pane\">\n  <div class=\"time-stamp entry-meta\">\n    <a href=\"joke-StlguCwk.html\">\n      <time datetime=\"2018-03-06T05:17:03.766Z\">2018-3-6 00:17:03</time>\n    </a>\n  </div><div class=\"text-caption\">Knock knock!\n    Who's there?\nHarvard University\n    Harvard University who?\nHarvard university majors!</div>\n</li>","postedSingleVideoPage":true},{"id":"joke-BeSwrpCL","date":"2018-03-06T08:17:02.985Z","caption":"Knock knock!\n    Who's there?\nPathans\n    Pathans who?\nPathans history!","postedToGit":true,"htmlFragment":"<li class=\"pane\">\n  <div class=\"time-stamp entry-meta\">\n    <a href=\"joke-BeSwrpCL.html\">\n      <time datetime=\"2018-03-06T08:17:02.985Z\">2018-3-6 03:17:02</time>\n    </a>\n  </div><div class=\"text-caption\">Knock knock!\n    Who's there?\nPathans\n    Pathans who?\nPathans history!</div>\n</li>","postedSingleVideoPage":true},{"id":"joke-vfbxqysz","date":"2018-03-06T11:17:03.312Z","caption":"Knock knock!\n    Who's there?\nBeest\n    Beest who?\nBee stinger!","postedToGit":true,"htmlFragment":"<li class=\"pane\">\n  <div class=\"time-stamp entry-meta\">\n    <a href=\"joke-vfbxqysz.html\">\n      <time datetime=\"2018-03-06T11:17:03.312Z\">2018-3-6 06:17:03</time>\n    </a>\n  </div><div class=\"text-caption\">Knock knock!\n    Who's there?\nBeest\n    Beest who?\nBee stinger!</div>\n</li>","postedSingleVideoPage":true},{"id":"joke-IXWIJAci","date":"2018-03-06T14:17:03.109Z","caption":"Knock knock!\n    Who's there?\nAdmissions\n    Admissions who?\nAdmissions calculator!","postedToGit":true,"htmlFragment":"<li class=\"pane\">\n  <div class=\"time-stamp entry-meta\">\n    <a href=\"joke-IXWIJAci.html\">\n      <time datetime=\"2018-03-06T14:17:03.109Z\">2018-3-6 09:17:03</time>\n    </a>\n  </div><div class=\"text-caption\">Knock knock!\n    Who's there?\nAdmissions\n    Admissions who?\nAdmissions calculator!</div>\n</li>","postedSingleVideoPage":true},{"id":"joke-SnKWynht","date":"2018-03-06T17:17:03.429Z","caption":"Knock knock!\n    Who's there?\nOrestes\n    Orestes who?\nOrestes 2.0!","postedToGit":true,"htmlFragment":"<li class=\"pane\">\n  <div class=\"time-stamp entry-meta\">\n    <a href=\"joke-SnKWynht.html\">\n      <time datetime=\"2018-03-06T17:17:03.429Z\">2018-3-6 12:17:03</time>\n    </a>\n  </div><div class=\"text-caption\">Knock knock!\n    Who's there?\nOrestes\n    Orestes who?\nOrestes 2.0!</div>\n</li>","postedSingleVideoPage":true},{"id":"joke-pIjvsQIx","date":"2018-03-06T20:17:02.591Z","caption":"Knock knock!\n    Who's there?\nMissouri River\n    Missouri River who?\nMissouri river city!","postedToGit":true,"htmlFragment":"<li class=\"pane\">\n  <div class=\"time-stamp entry-meta\">\n    <a href=\"joke-pIjvsQIx.html\">\n      <time datetime=\"2018-03-06T20:17:02.591Z\">2018-3-6 15:17:02</time>\n    </a>\n  </div><div class=\"text-caption\">Knock knock!\n    Who's there?\nMissouri River\n    Missouri River who?\nMissouri river city!</div>\n</li>","postedSingleVideoPage":true},{"id":"joke-DCuTbAlC","date":"2018-03-06T23:17:03.534Z","caption":"Knock knock!\n    Who's there?\nCushing\n    Cushing who?\nCushing academy hockey!","postedToGit":true,"htmlFragment":"<li class=\"pane\">\n  <div class=\"time-stamp entry-meta\">\n    <a href=\"joke-DCuTbAlC.html\">\n      <time datetime=\"2018-03-06T23:17:03.534Z\">2018-3-6 18:17:03</time>\n    </a>\n  </div><div class=\"text-caption\">Knock knock!\n    Who's there?\nCushing\n    Cushing who?\nCushing academy hockey!</div>\n</li>","postedSingleVideoPage":true},{"id":"joke-TRPXYQwW","date":"2018-03-07T02:17:03.390Z","caption":"Knock knock!\n    Who's there?\nJordanians\n    Jordanians who?\nJordanians are palestinian!","postedToGit":true,"htmlFragment":"<li class=\"pane\">\n  <div class=\"time-stamp entry-meta\">\n    <a href=\"joke-TRPXYQwW.html\">\n      <time datetime=\"2018-03-07T02:17:03.390Z\">2018-3-6 21:17:03</time>\n    </a>\n  </div><div class=\"text-caption\">Knock knock!\n    Who's there?\nJordanians\n    Jordanians who?\nJordanians are palestinian!</div>\n</li>","postedSingleVideoPage":true},{"id":"joke-ggUZpANd","date":"2018-03-07T05:17:03.568Z","caption":"Knock knock!\n    Who's there?\nLeonidas\n    Leonidas who?\nLeonidas kavakos!","postedToGit":true,"htmlFragment":"<li class=\"pane\">\n  <div class=\"time-stamp entry-meta\">\n    <a href=\"joke-ggUZpANd.html\">\n      <time datetime=\"2018-03-07T05:17:03.568Z\">2018-3-7 00:17:03</time>\n    </a>\n  </div><div class=\"text-caption\">Knock knock!\n    Who's there?\nLeonidas\n    Leonidas who?\nLeonidas kavakos!</div>\n</li>","postedSingleVideoPage":true},{"id":"joke-bHEVoiPb","date":"2018-03-07T08:17:03.276Z","caption":"Knock knock!\n    Who's there?\nGabor\n    Gabor who?\nGabor szabo!","postedToGit":true,"htmlFragment":"<li class=\"pane\">\n  <div class=\"time-stamp entry-meta\">\n    <a href=\"joke-bHEVoiPb.html\">\n      <time datetime=\"2018-03-07T08:17:03.276Z\">2018-3-7 03:17:03</time>\n    </a>\n  </div><div class=\"text-caption\">Knock knock!\n    Who's there?\nGabor\n    Gabor who?\nGabor szabo!</div>\n</li>","postedSingleVideoPage":true},{"id":"joke-KRWFtyxH","date":"2018-03-07T11:17:02.692Z","caption":"Knock knock!\n    Who's there?\nArchaeology\n    Archaeology who?\nArchaeology wow!","postedToGit":true,"htmlFragment":"<li class=\"pane\">\n  <div class=\"time-stamp entry-meta\">\n    <a href=\"joke-KRWFtyxH.html\">\n      <time datetime=\"2018-03-07T11:17:02.692Z\">2018-3-7 06:17:02</time>\n    </a>\n  </div><div class=\"text-caption\">Knock knock!\n    Who's there?\nArchaeology\n    Archaeology who?\nArchaeology wow!</div>\n</li>","postedSingleVideoPage":true},{"id":"joke-uwgHdHDV","date":"2018-03-07T14:17:02.968Z","caption":"Knock knock!\n    Who's there?\nAlbondigas\n    Albondigas who?\nAlbondigas dominicanas!","postedToGit":true,"htmlFragment":"<li class=\"pane\">\n  <div class=\"time-stamp entry-meta\">\n    <a href=\"joke-uwgHdHDV.html\">\n      <time datetime=\"2018-03-07T14:17:02.968Z\">2018-3-7 09:17:02</time>\n    </a>\n  </div><div class=\"text-caption\">Knock knock!\n    Who's there?\nAlbondigas\n    Albondigas who?\nAlbondigas dominicanas!</div>\n</li>","postedSingleVideoPage":true},{"id":"joke-xIknwROB","date":"2018-03-07T17:17:03.206Z","caption":"Knock knock!\n    Who's there?\nQueenslander\n    Queenslander who?\nQueensland heeler!","postedToGit":true,"htmlFragment":"<li class=\"pane\">\n  <div class=\"time-stamp entry-meta\">\n    <a href=\"joke-xIknwROB.html\">\n      <time datetime=\"2018-03-07T17:17:03.206Z\">2018-3-7 12:17:03</time>\n    </a>\n  </div><div class=\"text-caption\">Knock knock!\n    Who's there?\nQueenslander\n    Queenslander who?\nQueensland heeler!</div>\n</li>","postedSingleVideoPage":true},{"id":"joke-AWIkqHyf","date":"2018-03-07T20:17:02.811Z","caption":"Knock knock!\n    Who's there?\nBayberry\n    Bayberry who?\nBayberry bush!","postedToGit":true,"htmlFragment":"<li class=\"pane\">\n  <div class=\"time-stamp entry-meta\">\n    <a href=\"joke-AWIkqHyf.html\">\n      <time datetime=\"2018-03-07T20:17:02.811Z\">2018-3-7 15:17:02</time>\n    </a>\n  </div><div class=\"text-caption\">Knock knock!\n    Who's there?\nBayberry\n    Bayberry who?\nBayberry bush!</div>\n</li>","postedSingleVideoPage":true}]